autocommit/__init__.py
autocommit/autocommit.py
autocommit/src/llm_wrapper.py
autocommit/src/prompts.py
autogen_commit-0.1.0.dist-info/METADATA
autogen_commit-0.1.0.dist-info/WHEEL
autogen_commit-0.1.0.dist-info/licenses/LICENSE
autogen_commit-0.1.0.dist-info/RECORD
