Metadata-Version: 2.3
Name: autogen-commit
Version: 0.1.0
Summary: Auto-generate git commit messages
Project-URL: Homepage, https://github.com/raghavpillai/autocommit
Project-URL: Issues, https://github.com/raghavpillai/autocommit/issues
Author-email: Raghav Pillai <raghav@tryspeck.com>
License: MIT License
License-File: LICENSE
Classifier: License :: OSI Approved :: MIT License
Classifier: Operating System :: OS Independent
Classifier: Programming Language :: Python :: 3
Requires-Python: >=3.11
Requires-Dist: anthropic
Requires-Dist: openai
